easy_pagination/__init__.py
easy_pagination/pagination.py
easy_pagination/tests/__init__.py
easy_pagination/tests/settings.py
easy_pagination/tests/test_pagination.py
easy_pagination-0.1.0.dist-info/licenses/LICENSE
easy_pagination-0.1.0.dist-info/METADATA
easy_pagination-0.1.0.dist-info/WHEEL
easy_pagination-0.1.0.dist-info/top_level.txt
easy_pagination-0.1.0.dist-info/RECORD
